[
    {
      "username": "milf_emily",
      "email": "milfemily@1234",
      "password:": "1234",
      "zip": "55437"
    },
    {
        "username": "john",
        "email": "john_doe@gmail.com",
        "password:": "4321",
        "zip": "55438"
      },
    {
        "username": "i_hate_dogs",
        "email": "ihatedogs@gmail.com",
        "password:": "2222",
        "zip": "46786"
    },
    {
        "username": "kurt_cobain",
        "email": "thereal@kurtcobain",
        "password:": "9999",
        "zip": "55125"
    }
  ]
  